heysummit/__init__.py
heysummit/api.py
heysummit-0.1.4.dist-info/LICENSE
heysummit-0.1.4.dist-info/WHEEL
heysummit-0.1.4.dist-info/METADATA
heysummit-0.1.4.dist-info/RECORD
