Metadata-Version: 2.1
Name: heysummit
Version: 0.1.4
Summary: HeySummit API Client
Home-page: https://github.com/fzipi/hey-summit
License: Apache-2.0
Author: Felipe Zipitria
Author-email: felipe.zipitria@owasp.org
Requires-Python: >=3.6,<4.0
Classifier: License :: OSI Approved :: Apache Software License
Classifier: Programming Language :: Python :: 3
Classifier: Programming Language :: Python :: 3.6
Classifier: Programming Language :: Python :: 3.7
Classifier: Programming Language :: Python :: 3.8
Requires-Dist: requests (>=2.23.0,<3.0.0)
Project-URL: Repository, https://github.com/fzipi/hey-summit
